gmailsweep/__init__.py
gmailsweep/app.py
gmailsweep/auth.py
gmailsweep/cli.py
gmailsweep/logic.py
gmailsweep-0.1.0.dist-info/licenses/LICENSE
gmailsweep-0.1.0.dist-info/METADATA
gmailsweep-0.1.0.dist-info/WHEEL
gmailsweep-0.1.0.dist-info/entry_points.txt
gmailsweep-0.1.0.dist-info/top_level.txt
gmailsweep-0.1.0.dist-info/RECORD
