Metadata-Version: 2.4
Name: gmailsweep
Version: 0.1.0
Summary: Automated Gmail cleanup tool with Streamlit UI
Author-email: M J Shetty <mjgit007@gmail.com>
Project-URL: Homepage, https://github.com/mjgit007/gmailsweep
Project-URL: Bug Tracker, https://github.com/mjgit007/gmailsweep/issues
Classifier: Programming Language :: Python :: 3
Classifier: License :: OSI Approved :: MIT License
Classifier: Operating System :: OS Independent
Requires-Python: >=3.9
License-File: LICENSE
Requires-Dist: streamlit>=1.39.0
Requires-Dist: pandas>=2.0.0
Requires-Dist: google-api-python-client>=2.0.0
Requires-Dist: google-auth-oauthlib>=1.0.0
Dynamic: license-file
